binalyzer_rest/__init__.py
binalyzer_rest/cli.py
binalyzer_rest/rest.py
binalyzer_rest/utils.py
binalyzer_rest/resources/health.yml
binalyzer_rest/resources/transform.yml
binalyzer_rest-1.0.0.data/data/CHANGELOG.md
binalyzer_rest-1.0.0.dist-info/AUTHORS
binalyzer_rest-1.0.0.dist-info/LICENSE.rst
binalyzer_rest-1.0.0.dist-info/METADATA
binalyzer_rest-1.0.0.dist-info/WHEEL
binalyzer_rest-1.0.0.dist-info/entry_points.txt
binalyzer_rest-1.0.0.dist-info/top_level.txt
binalyzer_rest-1.0.0.dist-info/RECORD
