Metadata-Version: 2.1
Name: binalyzer-rest
Version: 1.0.0
Summary: Binary Data Analyzer
Home-page: https://binalyzer.denisvasilik.com
Author: Denis Vasilìk
Author-email: contact@denisvasilik.com
License: UNKNOWN
Project-URL: Bug Tracker, https://github.com/denisvasilik/binalyzer/issues/
Project-URL: Documentation, https://binalyzer.readthedocs.io/en/latest/
Project-URL: Source Code, https://github.com/denisvasilik/binalyzer/
Platform: UNKNOWN
Classifier: Programming Language :: Python :: 3.6
Classifier: Operating System :: POSIX :: Linux
Requires-Dist: binalyzer
Requires-Dist: click (>=5.1)
Requires-Dist: flask (>=1.0)
Requires-Dist: flasgger (>=0.9.3)
Requires-Dist: jsonschema (>=2.6.0)
Requires-Dist: requests (>=2.25.1)
